{"data":[{"coloraxis":"coloraxis","name":"0","x":["All Beauty","All Electronics","Appliances","Arts, Crafts & Sewing","Automotive","Baby","Baby Products","Beauty","Cell Phones & Accessories","Clothing, Shoes & Jewelry","Electronics","Grocery & Gourmet Food","Health & Personal Care","Industrial & Scientific","Musical Instruments","Office Products","Patio, Lawn & Garden","Pet Supplies","Sports & Outdoors","Tools & Home Improvement","Toys & Games"],"y":["All Beauty","All Electronics","Appliances","Arts, Crafts & Sewing","Automotive","Baby","Baby Products","Beauty","Cell Phones & Accessories","Clothing, Shoes & Jewelry","Electronics","Grocery & Gourmet Food","Health & Personal Care","Industrial & Scientific","Musical Instruments","Office Products","Patio, Lawn & Garden","Pet Supplies","Sports & Outdoors","Tools & Home Improvement","Toys & Games"],"z":{"dtype":"f4","bdata":"AQCAP78vfj8Wan4\u002f+95+PwnMfj\u002fR334\u002fbR9\u002fP2KSfz+bLH4\u002fTGF+P4Zdfj+M3n4\u002fu+t+P97ifj+huX4\u002ffjR+P2SKfj\u002fsGn8\u002fPLN+P7p0fj+jYH4\u002fvy9+P\u002f3\u002ffz9SR38\u002fMeN+P39Yfz9man4\u002fhqV+P8hCfj95Vn8\u002fb69+P0Ntfz82B34\u002fryp+Pzw0fz9+WH8\u002f40V\u002fP6M0fz+Vxn4\u002fvyV\u002fP5k2fz9kKX4\u002fFmp+P1JHfz8DAIA\u002fou9+P9hGfz8Ffn4\u002fWdZ+P0t6fj\u002fH5n4\u002f7MR+P4wUfz9RC34\u002fiwF+PzZZfz8jUn8\u002f0+l+P31tfz8mt34\u002faDp\u002fP8Fjfz+F+X0\u002f+95+PzHjfj+i734\u002f\u002fv9\u002fP\u002fZJfz8kJ38\u002fEFp\u002fP\u002fupfj\u002fQk34\u002f2pF+Pzisfj\u002f2s34\u002fZPh+P\u002f1xfz+pP38\u002fcgN\u002fP7AHfz9BcX8\u002fml1\u002fPx3+fj8w834\u002fCcx+P39Yfz\u002fYRn8\u002f9kl\u002fP\u002f7\u002ffz+nCn8\u002f+DJ\u002fP26Yfj8pQH8\u002f\u002fBJ\u002fP8Zgfz\u002fftH4\u002ffrZ+PyR2fz+\u002fb38\u002fogF\u002fP05mfz9MJ38\u002fSIp\u002fP9Rhfz+9w34\u002f0d9+P2Zqfj8Ffn4\u002fJCd\u002fP6cKfz\u002f\u002f\u002f38\u002fA5h\u002fPzuCfj+mgH4\u002f5AV\u002fP6Fxfj9Jv34\u002f5pp+P9vffj+MrX4\u002fuNB+Py7vfj93Fn8\u002fmSZ\u002fP6rFfj\u002fKEH8\u002fbR9\u002fP4alfj9Z1n4\u002fEFp\u002fP\u002fgyfz8DmH8\u002f\u002fv9\u002fP1btfj9qdH4\u002faPh+Pzisfj9YB38\u002fIvF+PxQ5fz9m934\u002fnAh\u002fP80Pfz9eZH8\u002f9jd\u002fP8ECfz8pOH8\u002fYpJ\u002fP8hCfj9Len4\u002f+6l+P26Yfj87gn4\u002fVu1+PwAAgD\u002f3930\u002fNP19P\u002fNyfj\u002fGzX4\u002fqCB\u002fPw\u002fhfj8wun4\u002f+yt+P0xnfj+OEX8\u002fTF1+P2Refj9M530\u002fmyx+P3lWfz\u002fH5n4\u002f0JN+PylAfz+mgH4\u002fanR+P\u002ff3fT\u002f6\u002f38\u002fBsh+P8cufz9I430\u002fCet9PyzYfj++9n4\u002fy79+P4D0fj8RhH4\u002fuTB\u002fP4\u002fZfj\u002ffDn4\u002fTGF+P2+vfj\u002fsxH4\u002f2pF+P\u002fwSfz\u002fkBX8\u002faPh+PzT9fT8GyH4\u002f\u002ff9\u002fP36Afj\u002fjN34\u002fq459P5Wlfj+S8H4\u002fO45+P9oXfz\u002f4Pn4\u002fETd\u002fP2cIfz\u002fXdX4\u002fhl1+P0Ntfz+MFH8\u002fOKx+P8Zgfz+hcX4\u002fOKx+P\u002fNyfj\u002fHLn8\u002ffoB+P\u002f7\u002ffz+FIX4\u002fQXh+Pz0qfz81JH8\u002fUQN\u002fP6b8fj8kzX4\u002f7Ax\u002fP84Dfz+3\u002fX0\u002fjN5+PzYHfj9RC34\u002f9rN+P9+0fj9Jv34\u002fWAd\u002fP8bNfj9I430\u002f4zd+P4Uhfj\u002f7\u002f38\u002frsR+P8F3fj94Un4\u002fgEl+P785fj+pHX8\u002fDFZ+P0wEfj\u002fU0H4\u002fu+t+P68qfj+LAX4\u002fZPh+P362fj\u002fmmn4\u002fIvF+P6ggfz8J630\u002fq459P0F4fj+uxH4\u002fAACAP0rwfj\u002fGc34\u002fJUN+P4olfj8YY38\u002fXGx+Pwswfj+qFX4\u002f3uJ+Pzw0fz82WX8\u002f\u002fXF\u002fPyR2fz\u002fb334\u002fFDl\u002fPw\u002fhfj8s2H4\u002flaV+Pz0qfz\u002fBd34\u002fSvB+PwMAgD9Icn8\u002fie5+PwBafz+SRX8\u002fKHV\u002fP4Vffz8zl34\u002fobl+P35Yfz8jUn8\u002fqT9\u002fP79vfz+MrX4\u002fZvd+PzC6fj++9n4\u002fkvB+PzUkfz94Un4\u002fxnN+P0hyfz\u002f+\u002f38\u002fget+P4ZAfz+74n4\u002fg2d\u002fP\u002fdRfz\u002fRcn4\u002ffjR+P+NFfz\u002fT6X4\u002fcgN\u002fP6IBfz+40H4\u002fnAh\u002fP\u002fsrfj\u002fLv34\u002fO45+P1EDfz+ASX4\u002fJUN+P4nufj+B634\u002f\u002f\u002f9\u002fP4DNfj8B7X4\u002fd\u002fp+P2\u002fLfj\u002f7pn4\u002fZIp+P6M0fz99bX8\u002fsAd\u002fP05mfz8u734\u002fzQ9\u002fP0xnfj+A9H4\u002f2hd\u002fP6b8fj+\u002fOX4\u002fiiV+PwBafz+GQH8\u002fgM1+P\u002fz\u002ffz8FvH4\u002fymx\u002fPw2Jfz96SH4\u002f7Bp\u002fP5XGfj8mt34\u002fQXF\u002fP0wnfz93Fn8\u002fXmR\u002fP44Rfz8RhH4\u002f+D5+PyTNfj+pHX8\u002fGGN\u002fP5JFfz+74n4\u002fAe1+PwW8fj8AAIA\u002fzAV\u002fP0K6fj+S8n4\u002fPLN+P78lfz9oOn8\u002fml1\u002fP0iKfz+ZJn8\u002f9jd\u002fP0xdfj+5MH8\u002fETd\u002fP+wMfz8MVn4\u002fXGx+Pyh1fz+DZ38\u002fd\u002fp+P8psfz\u002fMBX8\u002fAQCAP6F8fz8hx34\u002funR+P5k2fz\u002fBY38\u002fHf5+P9Rhfz+qxX4\u002fwQJ\u002fP2Refj+P2X4\u002fZwh\u002fP84Dfz9MBH4\u002fCzB+P4Vffz\u002f3UX8\u002fb8t+Pw2Jfz9Cun4\u002foXx\u002fP\u002f\u002f\u002ffz\u002f0Qn4\u002fo2B+P2Qpfj+F+X0\u002fMPN+P73Dfj\u002fKEH8\u002fKTh\u002fP0znfT\u002ffDn4\u002f13V+P7f9fT\u002fU0H4\u002fqhV+PzOXfj\u002fRcn4\u002f+6Z+P3pIfj+S8n4\u002fIcd+P\u002fRCfj8AAIA\u002f","shape":"21, 21"},"type":"heatmap","xaxis":"x","yaxis":"y","hovertemplate":"x: %{x}\u003cbr\u003ey: %{y}\u003cbr\u003eSimilarity: %{z}\u003cextra\u003e\u003c\u002fextra\u003e"}],"layout":{"template":{"data":{"histogram2dcontour":[{"type":"histogram2dcontour","colorbar":{"outlinewidth":0,"ticks":""},"colorscale":[[0.0,"#0d0887"],[0.1111111111111111,"#46039f"],[0.2222222222222222,"#7201a8"],[0.3333333333333333,"#9c179e"],[0.4444444444444444,"#bd3786"],[0.5555555555555556,"#d8576b"],[0.6666666666666666,"#ed7953"],[0.7777777777777778,"#fb9f3a"],[0.8888888888888888,"#fdca26"],[1.0,"#f0f921"]]}],"choropleth":[{"type":"choropleth","colorbar":{"outlinewidth":0,"ticks":""}}],"histogram2d":[{"type":"histogram2d","colorbar":{"outlinewidth":0,"ticks":""},"colorscale":[[0.0,"#0d0887"],[0.1111111111111111,"#46039f"],[0.2222222222222222,"#7201a8"],[0.3333333333333333,"#9c179e"],[0.4444444444444444,"#bd3786"],[0.5555555555555556,"#d8576b"],[0.6666666666666666,"#ed7953"],[0.7777777777777778,"#fb9f3a"],[0.8888888888888888,"#fdca26"],[1.0,"#f0f921"]]}],"heatmap":[{"type":"heatmap","colorbar":{"outlinewidth":0,"ticks":""},"colorscale":[[0.0,"#0d0887"],[0.1111111111111111,"#46039f"],[0.2222222222222222,"#7201a8"],[0.3333333333333333,"#9c179e"],[0.4444444444444444,"#bd3786"],[0.5555555555555556,"#d8576b"],[0.6666666666666666,"#ed7953"],[0.7777777777777778,"#fb9f3a"],[0.8888888888888888,"#fdca26"],[1.0,"#f0f921"]]}],"contourcarpet":[{"type":"contourcarpet","colorbar":{"outlinewidth":0,"ticks":""}}],"contour":[{"type":"contour","colorbar":{"outlinewidth":0,"ticks":""},"colorscale":[[0.0,"#0d0887"],[0.1111111111111111,"#46039f"],[0.2222222222222222,"#7201a8"],[0.3333333333333333,"#9c179e"],[0.4444444444444444,"#bd3786"],[0.5555555555555556,"#d8576b"],[0.6666666666666666,"#ed7953"],[0.7777777777777778,"#fb9f3a"],[0.8888888888888888,"#fdca26"],[1.0,"#f0f921"]]}],"surface":[{"type":"surface","colorbar":{"outlinewidth":0,"ticks":""},"colorscale":[[0.0,"#0d0887"],[0.1111111111111111,"#46039f"],[0.2222222222222222,"#7201a8"],[0.3333333333333333,"#9c179e"],[0.4444444444444444,"#bd3786"],[0.5555555555555556,"#d8576b"],[0.6666666666666666,"#ed7953"],[0.7777777777777778,"#fb9f3a"],[0.8888888888888888,"#fdca26"],[1.0,"#f0f921"]]}],"mesh3d":[{"type":"mesh3d","colorbar":{"outlinewidth":0,"ticks":""}}],"scatter":[{"fillpattern":{"fillmode":"overlay","size":10,"solidity":0.2},"type":"scatter"}],"parcoords":[{"type":"parcoords","line":{"colorbar":{"outlinewidth":0,"ticks":""}}}],"scatterpolargl":[{"type":"scatterpolargl","marker":{"colorbar":{"outlinewidth":0,"ticks":""}}}],"bar":[{"error_x":{"color":"#2a3f5f"},"error_y":{"color":"#2a3f5f"},"marker":{"line":{"color":"white","width":0.5},"pattern":{"fillmode":"overlay","size":10,"solidity":0.2}},"type":"bar"}],"scattergeo":[{"type":"scattergeo","marker":{"colorbar":{"outlinewidth":0,"ticks":""}}}],"scatterpolar":[{"type":"scatterpolar","marker":{"colorbar":{"outlinewidth":0,"ticks":""}}}],"histogram":[{"marker":{"pattern":{"fillmode":"overlay","size":10,"solidity":0.2}},"type":"histogram"}],"scattergl":[{"type":"scattergl","marker":{"colorbar":{"outlinewidth":0,"ticks":""}}}],"scatter3d":[{"type":"scatter3d","line":{"colorbar":{"outlinewidth":0,"ticks":""}},"marker":{"colorbar":{"outlinewidth":0,"ticks":""}}}],"scattermap":[{"type":"scattermap","marker":{"colorbar":{"outlinewidth":0,"ticks":""}}}],"scattermapbox":[{"type":"scattermapbox","marker":{"colorbar":{"outlinewidth":0,"ticks":""}}}],"scatterternary":[{"type":"scatterternary","marker":{"colorbar":{"outlinewidth":0,"ticks":""}}}],"scattercarpet":[{"type":"scattercarpet","marker":{"colorbar":{"outlinewidth":0,"ticks":""}}}],"carpet":[{"aaxis":{"endlinecolor":"#2a3f5f","gridcolor":"#C8D4E3","linecolor":"#C8D4E3","minorgridcolor":"#C8D4E3","startlinecolor":"#2a3f5f"},"baxis":{"endlinecolor":"#2a3f5f","gridcolor":"#C8D4E3","linecolor":"#C8D4E3","minorgridcolor":"#C8D4E3","startlinecolor":"#2a3f5f"},"type":"carpet"}],"table":[{"cells":{"fill":{"color":"#EBF0F8"},"line":{"color":"white"}},"header":{"fill":{"color":"#C8D4E3"},"line":{"color":"white"}},"type":"table"}],"barpolar":[{"marker":{"line":{"color":"white","width":0.5},"pattern":{"fillmode":"overlay","size":10,"solidity":0.2}},"type":"barpolar"}],"pie":[{"automargin":true,"type":"pie"}]},"layout":{"autotypenumbers":"strict","colorway":["#636efa","#EF553B","#00cc96","#ab63fa","#FFA15A","#19d3f3","#FF6692","#B6E880","#FF97FF","#FECB52"],"font":{"color":"#2a3f5f"},"hovermode":"closest","hoverlabel":{"align":"left"},"paper_bgcolor":"white","plot_bgcolor":"white","polar":{"bgcolor":"white","angularaxis":{"gridcolor":"#EBF0F8","linecolor":"#EBF0F8","ticks":""},"radialaxis":{"gridcolor":"#EBF0F8","linecolor":"#EBF0F8","ticks":""}},"ternary":{"bgcolor":"white","aaxis":{"gridcolor":"#DFE8F3","linecolor":"#A2B1C6","ticks":""},"baxis":{"gridcolor":"#DFE8F3","linecolor":"#A2B1C6","ticks":""},"caxis":{"gridcolor":"#DFE8F3","linecolor":"#A2B1C6","ticks":""}},"coloraxis":{"colorbar":{"outlinewidth":0,"ticks":""}},"colorscale":{"sequential":[[0.0,"#0d0887"],[0.1111111111111111,"#46039f"],[0.2222222222222222,"#7201a8"],[0.3333333333333333,"#9c179e"],[0.4444444444444444,"#bd3786"],[0.5555555555555556,"#d8576b"],[0.6666666666666666,"#ed7953"],[0.7777777777777778,"#fb9f3a"],[0.8888888888888888,"#fdca26"],[1.0,"#f0f921"]],"sequentialminus":[[0.0,"#0d0887"],[0.1111111111111111,"#46039f"],[0.2222222222222222,"#7201a8"],[0.3333333333333333,"#9c179e"],[0.4444444444444444,"#bd3786"],[0.5555555555555556,"#d8576b"],[0.6666666666666666,"#ed7953"],[0.7777777777777778,"#fb9f3a"],[0.8888888888888888,"#fdca26"],[1.0,"#f0f921"]],"diverging":[[0,"#8e0152"],[0.1,"#c51b7d"],[0.2,"#de77ae"],[0.3,"#f1b6da"],[0.4,"#fde0ef"],[0.5,"#f7f7f7"],[0.6,"#e6f5d0"],[0.7,"#b8e186"],[0.8,"#7fbc41"],[0.9,"#4d9221"],[1,"#276419"]]},"xaxis":{"gridcolor":"#EBF0F8","linecolor":"#EBF0F8","ticks":"","title":{"standoff":15},"zerolinecolor":"#EBF0F8","automargin":true,"zerolinewidth":2},"yaxis":{"gridcolor":"#EBF0F8","linecolor":"#EBF0F8","ticks":"","title":{"standoff":15},"zerolinecolor":"#EBF0F8","automargin":true,"zerolinewidth":2},"scene":{"xaxis":{"backgroundcolor":"white","gridcolor":"#DFE8F3","linecolor":"#EBF0F8","showbackground":true,"ticks":"","zerolinecolor":"#EBF0F8","gridwidth":2},"yaxis":{"backgroundcolor":"white","gridcolor":"#DFE8F3","linecolor":"#EBF0F8","showbackground":true,"ticks":"","zerolinecolor":"#EBF0F8","gridwidth":2},"zaxis":{"backgroundcolor":"white","gridcolor":"#DFE8F3","linecolor":"#EBF0F8","showbackground":true,"ticks":"","zerolinecolor":"#EBF0F8","gridwidth":2}},"shapedefaults":{"line":{"color":"#2a3f5f"}},"annotationdefaults":{"arrowcolor":"#2a3f5f","arrowhead":0,"arrowwidth":1},"geo":{"bgcolor":"white","landcolor":"white","subunitcolor":"#C8D4E3","showland":true,"showlakes":true,"lakecolor":"white"},"title":{"x":0.05},"mapbox":{"style":"light"}}},"xaxis":{"anchor":"y","domain":[0.0,1.0],"scaleanchor":"y","constrain":"domain","tickangle":-45},"yaxis":{"anchor":"x","domain":[0.0,1.0],"autorange":"reversed","constrain":"domain"},"coloraxis":{"colorbar":{"title":{"text":"Similarity"}},"colorscale":[[0.0,"#440154"],[0.1111111111111111,"#482878"],[0.2222222222222222,"#3e4989"],[0.3333333333333333,"#31688e"],[0.4444444444444444,"#26828e"],[0.5555555555555556,"#1f9e89"],[0.6666666666666666,"#35b779"],[0.7777777777777778,"#6ece58"],[0.8888888888888888,"#b5de2b"],[1.0,"#fde725"]]},"title":{"text":"Category Similarity Matrix (Cosine) - All 21 Classes"},"margin":{"l":150,"r":50,"t":60,"b":150},"width":1000,"height":1000}}